awehflow/__init__.py
awehflow/config.py
awehflow/core.py
awehflow/utils.py
awehflow/alerts/__init__.py
awehflow/alerts/base.py
awehflow/alerts/googlechat.py
awehflow/alerts/slack.py
awehflow/alerts/teams.py
awehflow/events/__init__.py
awehflow/events/alerts.py
awehflow/events/base.py
awehflow/events/gcp.py
awehflow/events/postgres.py
awehflow/operators/__init__.py
awehflow/operators/etl.py
awehflow/operators/flow.py
awehflow/operators/gcp.py
awehflow/operators/gcs.py
awehflow/operators/metrics.py
awehflow/operators/taxonomy.py
awehflow/sensors/__init__.py
awehflow/sensors/http.py
awehflow/sensors/sql_sensor.py
awehflow-4.0.5.dist-info/licenses/LICENSE
awehflow_cli/__init__.py
awehflow_cli/cli.py
awehflow_cli/config_scripts/__init__.py
awehflow_cli/config_scripts/generate_configs.py
awehflow_cli/config_scripts/utils.py
awehflow_cli/config_scripts/validate_configs.py
awehflow-4.0.5.dist-info/METADATA
awehflow-4.0.5.dist-info/WHEEL
awehflow-4.0.5.dist-info/entry_points.txt
awehflow-4.0.5.dist-info/top_level.txt
awehflow-4.0.5.dist-info/RECORD
