Metadata-Version: 2.4
Name: awehflow
Version: 4.0.5
Summary: Configuration based Apache Airflow
Home-page: 
Author: Philip Perold
Author-email: philip@spatialedge.co.za
Classifier: Programming Language :: Python :: 3
Classifier: Operating System :: OS Independent
Requires-Python: >=3.6
License-File: LICENSE
Requires-Dist: click==8.1.7
Requires-Dist: dotty-dict>=1.2.1
Requires-Dist: psycopg2-binary==2.9.10
Requires-Dist: pyhocon>=0.3.59
Requires-Dist: PyMySQL==1.1.1
Requires-Dist: pyyaml==6.0.2
Requires-Dist: slackclient>=2.5.0
Provides-Extra: default
Requires-Dist: apache-airflow==2.1.4; extra == "default"
Provides-Extra: composer
Requires-Dist: apache-airflow==2.1.4+composer; extra == "composer"
Dynamic: author
Dynamic: author-email
Dynamic: classifier
Dynamic: description
Dynamic: description-content-type
Dynamic: license-file
Dynamic: provides-extra
Dynamic: requires-dist
Dynamic: requires-python
Dynamic: summary
